liteflow.providers.mongo-0.3.1-py3.6-nspkg.pth
liteflow/providers/mongo/__init__.py
liteflow/providers/mongo/converters.py
liteflow/providers/mongo/mongo_persistence_provider.py
liteflow.providers.mongo-0.3.1.dist-info/METADATA
liteflow.providers.mongo-0.3.1.dist-info/RECORD
liteflow.providers.mongo-0.3.1.dist-info/WHEEL
liteflow.providers.mongo-0.3.1.dist-info/namespace_packages.txt
liteflow.providers.mongo-0.3.1.dist-info/top_level.txt
