Metadata-Version: 2.1
Name: liteflow.providers.mongo
Version: 0.3.1
Summary: MongoDB persistence provider for LiteFlow
Home-page: https://github.com/danielgerlag/liteflow
Author: Daniel Gerlag
Author-email: daniel@gerlag.ca
License: MIT
Platform: UNKNOWN
Classifier: Programming Language :: Python :: 3.6
Classifier: License :: OSI Approved :: MIT License
Classifier: Operating System :: OS Independent
Requires-Python: >=3.6
Requires-Dist: liteflow.core (>=0.3)
Requires-Dist: pymongo (>=3.6.1)
Requires-Dist: python-interface (>=1.4.0)
